kabbes_gmail/Connection.py
kabbes_gmail/Email.py
kabbes_gmail/__init__.py
kabbes_gmail/__main__.py
kabbes_gmail-0.1.0.dist-info/LICENSE
kabbes_gmail-0.1.0.dist-info/METADATA
kabbes_gmail-0.1.0.dist-info/WHEEL
kabbes_gmail-0.1.0.dist-info/top_level.txt
kabbes_gmail-0.1.0.dist-info/RECORD
