Metadata-Version: 2.1
Name: kabbes-gmail
Version: 0.1.0
Summary: Python connection to Gmail
Home-page: https://pypi.org/project/kabbes-gmail/
Author: James Kabbes
Author-email: james.kabbes@gmail.com
Project-URL: GitHub, https://github.com/jameskabbes/gmail
Project-URL: Documentation, https://jameskabbes.github.io/gmail
Classifier: Programming Language :: Python :: 3
Classifier: License :: OSI Approved :: MIT License
Classifier: Operating System :: OS Independent
Requires-Python: >=3.7
License-File: LICENSE
Requires-Dist: yagmail
Requires-Dist: kabbes-dir-ops
Requires-Dist: kabbes-parent-class
Requires-Dist: kabbes-py-starter
